stackalytics/__init__.py
stackalytics/version.py
stackalytics/dashboard/__init__.py
stackalytics/dashboard/config.py
stackalytics/dashboard/decorators.py
stackalytics/dashboard/helpers.py
stackalytics/dashboard/kpi.py
stackalytics/dashboard/memory_storage.py
stackalytics/dashboard/parameters.py
stackalytics/dashboard/reports.py
stackalytics/dashboard/vault.py
stackalytics/dashboard/web.py
stackalytics/dashboard/web.wsgi
stackalytics/dashboard/static/css/jquery.dataTables.css
stackalytics/dashboard/static/css/jquery.jqplot.min.css
stackalytics/dashboard/static/css/moonfonts.css
stackalytics/dashboard/static/css/select2.css
stackalytics/dashboard/static/css/style.css
stackalytics/dashboard/static/css/fonts/ostackportal_moon.eot
stackalytics/dashboard/static/css/fonts/ostackportal_moon.svg
stackalytics/dashboard/static/css/fonts/ostackportal_moon.ttf
stackalytics/dashboard/static/css/fonts/ostackportal_moon.woff
stackalytics/dashboard/static/css/jquery-ui/jquery-ui-1.10.4.custom.css
stackalytics/dashboard/static/css/jquery-ui/images/animated-overlay.gif
stackalytics/dashboard/static/css/jquery-ui/images/ui-bg_flat_0_aaaaaa_40x100.png
stackalytics/dashboard/static/css/jquery-ui/images/ui-bg_flat_75_ffffff_40x100.png
stackalytics/dashboard/static/css/jquery-ui/images/ui-bg_glass_55_fbf9ee_1x400.png
stackalytics/dashboard/static/css/jquery-ui/images/ui-bg_glass_65_ffffff_1x400.png
stackalytics/dashboard/static/css/jquery-ui/images/ui-bg_glass_75_dadada_1x400.png
stackalytics/dashboard/static/css/jquery-ui/images/ui-bg_glass_75_e6e6e6_1x400.png
stackalytics/dashboard/static/css/jquery-ui/images/ui-bg_glass_95_fef1ec_1x400.png
stackalytics/dashboard/static/css/jquery-ui/images/ui-bg_highlight-soft_75_cccccc_1x100.png
stackalytics/dashboard/static/css/jquery-ui/images/ui-icons_222222_256x240.png
stackalytics/dashboard/static/css/jquery-ui/images/ui-icons_2e83ff_256x240.png
stackalytics/dashboard/static/css/jquery-ui/images/ui-icons_454545_256x240.png
stackalytics-1.0.0.dist-info/AUTHORS
stackalytics-1.0.0.dist-info/LICENSE
stackalytics-1.0.0.dist-info/METADATA
stackalytics-1.0.0.dist-info/WHEEL
stackalytics-1.0.0.dist-info/entry_points.txt
stackalytics-1.0.0.dist-info/pbr.json
stackalytics-1.0.0.dist-info/top_level.txt
stackalytics-1.0.0.dist-info/RECORD
