Metadata-Version: 2.1
Name: stackalytics
Version: 1.0.0
Summary: OpenStack Contribution Dashboard
Home-page: https://www.openstack.org/
Author: OpenStack
Author-email: openstack-dev@lists.openstack.org
License: UNKNOWN
Platform: UNKNOWN
Classifier: Environment :: OpenStack
Classifier: Intended Audience :: Developers
Classifier: Intended Audience :: Information Technology
Classifier: License :: OSI Approved :: Apache Software License
Classifier: Operating System :: POSIX :: Linux
Classifier: Programming Language :: Python
Classifier: Programming Language :: Python :: 2
Classifier: Programming Language :: Python :: 2.7
Classifier: Programming Language :: Python :: 3
Classifier: Programming Language :: Python :: 3.5
Requires-Dist: pbr (>=2.0.0)
Requires-Dist: Babel (>=2.3.4)
Requires-Dist: Flask (!=0.11,<1.0,>=0.10)
Requires-Dist: iso8601 (>=0.1.11)
Requires-Dist: jsonschema (!=2.5.0,<3.0.0,>=2.0.0)
Requires-Dist: oslo.config (>=3.22.0)
Requires-Dist: oslo.i18n (>=2.1.0)
Requires-Dist: oslo.log (>=3.22.0)
Requires-Dist: oslo.serialization (>=1.10.0)
Requires-Dist: oslo.utils (>=3.20.0)
Requires-Dist: paramiko (>=2.0)
Requires-Dist: psutil (>=3.2.2)
Requires-Dist: PyGithub
Requires-Dist: python-memcached (>=1.56)
Requires-Dist: PyYAML (>=3.10.0)
Requires-Dist: requests (!=2.12.2,!=2.13.0,>=2.10.0)
Requires-Dist: requests-file
Requires-Dist: sh
Requires-Dist: six (>=1.9.0)
